svgmanip/__init__.py
svgmanip/_generator.py
svgmanip-0.0.12.dist-info/LICENSE.txt
svgmanip-0.0.12.dist-info/METADATA
svgmanip-0.0.12.dist-info/WHEEL
svgmanip-0.0.12.dist-info/top_level.txt
svgmanip-0.0.12.dist-info/RECORD
